mqtt_ingest_pipeline/__init__.py
mqtt_ingest_pipeline/assistant_data_transformer.py
mqtt_ingest_pipeline/iot_data_transformer.py
mqtt_ingest_pipeline/main.py
mqtt_ingest_pipeline/mqtt_data_pipeline.py
mqtt_ingest_pipeline/py.typed
mqtt_ingest_pipeline/utility.py
mqtt_ingest_pipeline-0.1.5.dist-info/licenses/LICENSE
mqtt_ingest_pipeline-0.1.5.dist-info/WHEEL
mqtt_ingest_pipeline-0.1.5.dist-info/entry_points.txt
mqtt_ingest_pipeline-0.1.5.dist-info/METADATA
mqtt_ingest_pipeline-0.1.5.dist-info/RECORD
