Metadata-Version: 2.4
Name: mqtt-ingest-pipeline
Version: 0.1.5
Summary: Collection of MQTT data transformers for home automation and IoT devices.
Keywords: mqtt,iot,home-automation,timescaledb
Author: stkr22
Author-email: stkr22 <stkr22@github.com>
License-Expression: GPL-3.0-only
License-File: LICENSE
Classifier: Development Status :: 3 - Alpha
Classifier: Environment :: Console
Classifier: Programming Language :: Python
Classifier: Intended Audience :: Developers
Classifier: Operating System :: OS Independent
Classifier: Topic :: Home Automation
Requires-Dist: aiomqtt~=2.5.0
Requires-Dist: asyncpg~=0.31.0
Requires-Dist: sqlmodel~=0.0.22
Requires-Dist: typer~=0.21.0
Requires-Python: >=3.12, <3.14
Project-URL: Changelog, https://github.com/stkr22/mqtt-ingest-pipeline-py/blob/main/CHANGELOG.md
Project-URL: Documentation, https://github.com/stkr22/mqtt-ingest-pipeline-py/tree/main/docs
Project-URL: Homepage, https://github.com/stkr22/mqtt-ingest-pipeline-py
Project-URL: Issues, https://github.com/stkr22/mqtt-ingest-pipeline-py/issues
Project-URL: Repository, https://github.com/stkr22/mqtt-ingest-pipeline-py
